pypi_test_package/__init__.py
helin_peru_test_package-0.1.0.dist-info/METADATA
helin_peru_test_package-0.1.0.dist-info/WHEEL
helin_peru_test_package-0.1.0.dist-info/licenses/LICENSE
helin_peru_test_package-0.1.0.dist-info/RECORD
