Metadata-Version: 2.4
Name: helin-peru-test-package
Version: 0.1.0
Summary: A simple test package for PyPI publishing and Amazon Peru testing
Project-URL: Homepage, https://github.com/rpidhe/helin-peru-test-package
Project-URL: Repository, https://github.com/rpidhe/helin-peru-test-package
Project-URL: Issues, https://github.com/rpidhe/helin-peru-test-package/issues
Author-email: He Lin <2830585822@qq.com>
License-Expression: Apache-2.0
License-File: LICENSE
Classifier: Development Status :: 4 - Beta
Classifier: Intended Audience :: Developers
Classifier: License :: OSI Approved :: Apache Software License
Classifier: Programming Language :: Python :: 3
Classifier: Programming Language :: Python :: 3.12
Classifier: Topic :: Software Development :: Libraries :: Python Modules
Requires-Python: >=3.12
Provides-Extra: dev
Requires-Dist: pytest-cov>=4.0.0; extra == 'dev'
Requires-Dist: pytest>=7.0.0; extra == 'dev'
